plotter/__init__.py
plotter/plotter.py
plotter/utils.py
plotter/gtk3_plotter/__init__.py
plotter/gtk3_plotter/plot_selector.py
plotter-1.3.20.dist-info/LICENSE
plotter-1.3.20.dist-info/METADATA
plotter-1.3.20.dist-info/WHEEL
plotter-1.3.20.dist-info/top_level.txt
plotter-1.3.20.dist-info/RECORD
