Metadata-Version: 2.1
Name: plotter
Version: 1.3.20
Summary: Plotting library with descriptive approach
Home-page: https://plotter-doc.xyz
Author: Thomas Trouchkine
Author-email: thomas.trouchkine@gmail.com
Classifier: Programming Language :: Python :: 3
Classifier: Operating System :: OS Independent
License-File: LICENSE
